pymatgen/analysis/defects/__init__.py
pymatgen/analysis/defects/_version.py
pymatgen/analysis/defects/ccd.py
pymatgen/analysis/defects/constants.py
pymatgen/analysis/defects/core.py
pymatgen/analysis/defects/finder.py
pymatgen/analysis/defects/generators.py
pymatgen/analysis/defects/recombination.py
pymatgen/analysis/defects/supercells.py
pymatgen/analysis/defects/thermo.py
pymatgen/analysis/defects/utils.py
pymatgen/analysis/defects/corrections/__init__.py
pymatgen/analysis/defects/corrections/freysoldt.py
pymatgen/analysis/defects/corrections/kumagai.py
pymatgen/analysis/defects/plotting/__init__.py
pymatgen/analysis/defects/plotting/optics.py
pymatgen/analysis/defects/plotting/phases.py
pymatgen/analysis/defects/plotting/thermo.py
pymatgen/analysis/defects/plotting/utils.py
pymatgen_analysis_defects-2025.9.26.dist-info/licenses/LICENSE
pymatgen_analysis_defects-2025.9.26.dist-info/METADATA
pymatgen_analysis_defects-2025.9.26.dist-info/WHEEL
pymatgen_analysis_defects-2025.9.26.dist-info/top_level.txt
pymatgen_analysis_defects-2025.9.26.dist-info/RECORD
