Metadata-Version: 2.4
Name: pymatgen-analysis-defects
Version: 2025.9.26
Summary: Pymatgen extension for defects analysis
Author-email: Jimmy-Xuan Shen <jmmshn@gmail.com>
License: modified BSD
Project-URL: documentation, https://materialsproject.github.io/pymatgen-analysis-defects/
Project-URL: homepage, https://materialsproject.github.io/pymatgen-analysis-defects/
Project-URL: repository, https://github.com/materialsproject/pymatgen-analysis-defects
Keywords: high-throughput,automated,dft,defects
Classifier: Programming Language :: Python :: 3
Classifier: Programming Language :: Python :: 3.9
Classifier: Programming Language :: Python :: 3.10
Classifier: Programming Language :: Python :: 3.11
Classifier: Development Status :: 5 - Production/Stable
Classifier: Intended Audience :: Science/Research
Classifier: Operating System :: OS Independent
Classifier: Topic :: Other/Nonlisted Topic
Classifier: Topic :: Scientific/Engineering
Requires-Python: >=3.9
License-File: LICENSE
Requires-Dist: pymatgen>=2024.10.22
Requires-Dist: scikit-image>=0.19.3
Requires-Dist: numpy<3.0.0,>=2.0.0
Requires-Dist: mp-pyrho>=0.4.4
Provides-Extra: finder
Requires-Dist: dscribe>=2.0.0; extra == "finder"
Provides-Extra: dev
Requires-Dist: pre-commit>=2.12.1; extra == "dev"
Provides-Extra: docs
Requires-Dist: jupyter-book>=0.13.1; extra == "docs"
Provides-Extra: optional
Requires-Dist: pydefect; extra == "optional"
Requires-Dist: dscribe>=2.0.0; extra == "optional"
Requires-Dist: numba; extra == "optional"
Provides-Extra: tests
Requires-Dist: pytest>=8.2.1; extra == "tests"
Requires-Dist: pytest-cov>=5.0.0; extra == "tests"
Requires-Dist: nbmake>=1.5.3; extra == "tests"
Dynamic: license-file
